qattn/__init__.py
qattn/observer.py
qattn/quantize.py
qattn/backends_config/__init__.py
qattn/backends_config/qattn.py
qattn/fx/__init__.py
qattn/fx/lower.py
qattn/fx/qconfig.py
qattn/fx/transforms.py
qattn/nn/__init__.py
qattn/nn/functional/__init__.py
qattn/nn/functional/_flash_attention.py
qattn/nn/functional/_matmul.py
qattn/nn/functional/_matmul_configs.py
qattn/nn/functional/_quantize.py
qattn/nn/functional/_reference/__init__.py
qattn/nn/functional/_reference/attention.py
qattn/nn/functional/_reference/matmul.py
qattn/nn/functional/dynamic/__init__.py
qattn/nn/functional/dynamic/_matmul.py
qattn/nn/modules/__init__.py
qattn/nn/modules/linear.py
qattn/nn/modules/dynamic/__init__.py
qattn/nn/modules/dynamic/linear.py
qattn/pt2e/__init__.py
qattn/pt2e/annotators.py
qattn/pt2e/quantizer.py
qattn/pt2e/dynamo/backend/__init__.py
qattn/pt2e/dynamo/backend/backends.py
qattn-0.1.1.dist-info/LICENSE
qattn-0.1.1.dist-info/METADATA
qattn-0.1.1.dist-info/WHEEL
qattn-0.1.1.dist-info/top_level.txt
qattn-0.1.1.dist-info/RECORD
