Metadata-Version: 2.1
Name: qattn
Version: 0.1.1
Summary: Efficient GPU Kernels in Triton for Quantized Vision Transformers
Author-email: Piotr Kluska <klu@zurich.ibm.com>, Florian Scheidegger <eid@zurich.ibm.com>, "A. Cristiano I. Malossi" <acm@zurich.ibm.com>, "Enrique S. Quintana-Ortí" <quintana@disca.upv.es>
Maintainer-email: Piotr Kluska <klu@zurich.ibm.com>
License: MIT License
Project-URL: homepage, https://github.com/IBM/qattn
Project-URL: repository, https://github.com/IBM/qattn
Keywords: quantization,vision transformers,efficient,gpu
Classifier: Development Status :: 3 - Alpha
Classifier: Intended Audience :: Developers
Classifier: Topic :: Software Development
Classifier: License :: OSI Approved :: MIT License
Requires-Python: >=3.8
License-File: LICENSE
Requires-Dist: torch >=2.0
Requires-Dist: triton >=2.0
Requires-Dist: timm >=0.9
